database_mcp/__init__.py
database_mcp/__main__.py
database_mcp/mcp_server.py
prodify_sql_mcp-0.1.8.dist-info/licenses/LICENSE
prodify_sql_mcp-0.1.8.dist-info/METADATA
prodify_sql_mcp-0.1.8.dist-info/WHEEL
prodify_sql_mcp-0.1.8.dist-info/entry_points.txt
prodify_sql_mcp-0.1.8.dist-info/top_level.txt
prodify_sql_mcp-0.1.8.dist-info/RECORD
